helloworld.py
helloworldtest.py
helloworldnabeel-0.0.1.dist-info/METADATA
helloworldnabeel-0.0.1.dist-info/WHEEL
helloworldnabeel-0.0.1.dist-info/top_level.txt
helloworldnabeel-0.0.1.dist-info/RECORD
